bidly/__init__.py
bidly/bidding.py
bidly-0.6.dist-info/LICENSE
bidly-0.6.dist-info/METADATA
bidly-0.6.dist-info/WHEEL
bidly-0.6.dist-info/top_level.txt
bidly-0.6.dist-info/RECORD
