Metadata-Version: 2.1
Name: bidly
Version: 0.6
Summary: A bidding logic library for Django applications
Home-page: https://github.com/Priya-1110/bidly
Author: Priya Shanmugam
Author-email: priyashan112002@example.com
License: UNKNOWN
Platform: UNKNOWN
Classifier: Programming Language :: Python :: 3
Classifier: License :: OSI Approved :: MIT License
Classifier: Operating System :: OS Independent
Requires-Python: >=3.6
License-File: LICENSE
